asciime/__init__.py
asciime/__main__.py
asciime/core/__init__.py
asciime/core/cache_manager.py
asciime/core/config_manager.py
asciime/core/gif_fetcher.py
asciime/core/gif_player.py
asciime/core/gif_player_fast.py
asciime-0.1.0.dist-info/LICENSE
asciime-0.1.0.dist-info/METADATA
asciime-0.1.0.dist-info/WHEEL
asciime-0.1.0.dist-info/entry_points.txt
asciime-0.1.0.dist-info/top_level.txt
asciime-0.1.0.dist-info/RECORD
