Metadata-Version: 2.1
Name: asciime
Version: 0.1.0
Summary: Turn your terminal into a kawaii anime experience!
Author-email: Felix Dawodu <diamondfelix006@gmail.com>
License: MIT License
Project-URL: Homepage, https://github.com/Felixdiamond/asciime
Project-URL: Documentation, https://github.com/Felixdiamond/asciime#readme
Project-URL: Repository, https://github.com/Felixdiamond/asciime.git
Project-URL: Issues, https://github.com/Felixdiamond/asciime/issues
Keywords: ascii,anime,terminal,gif,cli
Classifier: Development Status :: 4 - Beta
Classifier: Environment :: Console
Classifier: Intended Audience :: End Users/Desktop
Classifier: License :: OSI Approved :: MIT License
Classifier: Operating System :: OS Independent
Classifier: Programming Language :: Python :: 3
Classifier: Programming Language :: Python :: 3.8
Classifier: Programming Language :: Python :: 3.9
Classifier: Programming Language :: Python :: 3.10
Classifier: Programming Language :: Python :: 3.11
Classifier: Programming Language :: Python :: 3.12
Classifier: Topic :: Terminals
Classifier: Topic :: Multimedia :: Graphics
Requires-Python: >=3.8
License-File: LICENSE
Requires-Dist: aiohttp>=3.8.0
Requires-Dist: Pillow>=9.0.0
Requires-Dist: rich>=10.0.0
Provides-Extra: dev
Requires-Dist: pytest>=7.0.0; extra == "dev"
Requires-Dist: pytest-asyncio>=0.18.0; extra == "dev"
Requires-Dist: pytest-cov>=3.0.0; extra == "dev"
Requires-Dist: black>=22.0.0; extra == "dev"
Requires-Dist: isort>=5.0.0; extra == "dev"
Requires-Dist: mypy>=0.900; extra == "dev"
Requires-Dist: ruff>=0.1.0; extra == "dev"
